{
  "ward_info": {
    "wardname": "Oke-Odo",
    "wardcode": "LASAMO31",
    "lganame": "Alimosho",
    "statename": "Lagos"
  },
  "time_series": [
    {
      "year_month": "2015-10",
      "event_count": 2,
      "total_fatalities": 1,
      "event_type_breakdown": {
        "Riots": 1,
        "Violence against civilians": 1
      }
    },
    {
      "year_month": "2021-09",
      "event_count": 1,
      "total_fatalities": 1,
      "event_type_breakdown": {
        "Riots": 1
      }
    },
    {
      "year_month": "2024-08",
      "event_count": 1,
      "total_fatalities": 0,
      "event_type_breakdown": {
        "Riots": 1
      }
    }
  ]
}